VitalSigns/BCPSS.py
VitalSigns/HUD.py
VitalSigns/__init__.py
VitalSigns/_nbdev.py
VitalSigns/acsDownload.py
VitalSigns/bidbaltimore.py
VitalSigns/bpd.py
VitalSigns/citistat.py
VitalSigns/cityfinance.py
VitalSigns/closecrawl.py
VitalSigns/create.py
VitalSigns/dhr.py
VitalSigns/enoch.py
VitalSigns/fares.py
VitalSigns/fdic.py
VitalSigns/indicators.py
VitalSigns/infousa.py
VitalSigns/liquor.py
VitalSigns/mdprop.py
VitalSigns/rbintel.py
VitalSigns/tidyaddr.py
VitalSigns/treebaltimore.py
VitalSigns/utils.py
VitalSigns-0.0.11.dist-info/LICENSE
VitalSigns-0.0.11.dist-info/METADATA
VitalSigns-0.0.11.dist-info/WHEEL
VitalSigns-0.0.11.dist-info/entry_points.txt
VitalSigns-0.0.11.dist-info/top_level.txt
VitalSigns-0.0.11.dist-info/RECORD
