Metadata-Version: 2.1
Name: VitalSigns
Version: 0.0.11
Summary: Python Scripts for BNIA-JFIs Vital Signs Data
Home-page: https://github.com/bnia/VitalSigns/tree/main/
Author: Charles Karpati
Author-email: charles.karpati@gmail.com
License: Apache Software License 2.0
Keywords: Community Data
Platform: UNKNOWN
Classifier: Development Status :: 3 - Alpha
Classifier: Intended Audience :: Developers
Classifier: Natural Language :: English
Classifier: Programming Language :: Python :: 3.6
Classifier: Programming Language :: Python :: 3.7
Classifier: Programming Language :: Python :: 3.8
Classifier: License :: OSI Approved :: Apache Software License
Requires-Python: >=3.6
License-File: LICENSE
Requires-Dist: pip
Requires-Dist: packaging
Provides-Extra: dev
